Workbook

Sheet Buyers FS
B3: INCOME | C3: STATEMENT
C4: 2020A | D4: 2021P
A5: REVENUE | C5: 450000 | D5: 504000
A6: GROWTH | D6: 0.12
A8: COGS | C8: 329824 | D8: 366399
A9: GROSS PROFIT | C9: =C5-C8 -> 120176 | D9: =D5-D8 -> 137601
A10: MARGIN | C10: 0.27 | D10: 0.27
A12: SG&A | C12: 58500 | D12: 60480
A13: SG&A AS % OF SALES | C13: 0.13 | D13: 0.12
A15: EBITDA | C15: =C9-C12 -> 61676 | D15: =D9-D12 -> 77121
A17: DEPRECIATION | C17: 2386 | D17: 2568
A18: DEP AS A % OF REVS | C18: 0.01 | D18: 0.01
A20: INTEREST | C20: =-D20 -> 0 | D20: 0
A21: PRE TAX INCOME | C21: =C15-C17 -> 59290 | D21: =D15-D17 -> 74553
A23: TAX | C23: 14823 | D23: 18638
A25: NET INCOME | C25: =C21-C23 -> 44467 | D25: =D21-D23 -> 55915
A26: AVG FD SHARES O/S | C26: 10000 | D26: 10000
A27: EPS | C27: 4.45 | D27: 5.59
A29: BALANCE SHEET
B30: 2020A
A31: CASH | B31: 50000
A32: ACCOUNTS RECEIVABLE | B32: 120000
A33: INVENTORY | B33: 25000
A34: CURRENT ASSESTS | B34: =B31+B32+B33 -> 195000
A36: NET PP&E | B36: 20000
A37: INTANGIABLE ASSESTS | B37: 0
A38: GOODWILL | B38: 0
A39: TOTAL ASSETS | B39: =B34+B36 -> 215000
A41: CURRENT LIABILITIES | B41: 130000
A42: BANK DEBT | B42: 0
A43: TOTAL LIABILITIES | B43: =B41+B42 -> 130000
A45: SHAREHOLDERS EQUITY | B45: 85000
A46: TOTAL LIABILITIES $SH EQUITY | B46: =B43+B45 -> 215000

Sheet Target FS
B3: INCOME | C3: STATEMENT
C4: 2020A | D4: 2021P
A5: REVENUE | C5: 132000 | D5: 157000
A6: GROWTH | D6: 0.19
A8: COGS | C8: 100480 | D8: 118980
A9: GROSS PROFIT | C9: =C5-C8 -> 31520 | D9: =D5-D8 -> 38020
A10: MARGIN | C10: 0.24 | D10: 0.24
A12: SG&A | C12: 22100 | D12: 25700
A13: SG&A AS % OF SALES | C13: 0.17 | D13: 0.16
A15: EBITDA | C15: =C9-C12 -> 9420 | D15: =D9-D12 -> 12320
A17: DEPRECIATION | C17: 700 | D17: 800
A18: DEP AS A % OF REVS | C18: 0.01 | D18: 0.01
A20: INTEREST | C20: 0 | D20: 0
A21: PRE TAX INCOME | C21: =C15-C17-C20 -> 8720 | D21: =D15-D17-D20 -> 11520
A23: TAX | C23: 2180 | D23: 2880
A25: NET INCOME | C25: =C21-C23 -> 6540 | D25: =D21-D23 -> 8640
A26: AVG FD SHARES O/S | C26: 1000 | D26: 1000
A27: EPS | C27: 6.54 | D27: 8.64
A29: BALANCE SHEET
B30: 2020A
A31: CASH | B31: 5000
A32: ACCOUNTS RECEIVABLE | B32: 25000
A33: INVENTORY | B33: 6000
A34: CURRENT ASSESTS | B34: =B31+B32+B33 -> 36000
A36: NET PP&E | B36: 7000
A37: INTANGIABLE ASSESTS | B37: 0
A38: GOODWILL | B38: 0
A39: TOTAL ASSETS | B39: =B36+B34 -> 43000
A41: CURRENT LIABILITIES | B41: 13000
A42: BANK DEBT | B42: 0
A43: TOTAL LIABILITIES | B43: =B41 -> 13000
A45: SHAREHOLDERS EQUITY | B45: 30000
A46: TOTAL LIABILITIES $SH EQUITY | B46: =B43+B45 -> 43000

Sheet ASSUMPTIONS
D3: TRANSACTION ASSUMPTIONS
A4: TARGET 2020 EPS | D4: 6.54 | E4: INTANGIABLE ASSEST AMORTIZATION
A5: P/E RATIO ON 2020 EPS | D5: 15 | E5: PURCAHSE PRICE OF TARGET EQUITY | I5: 127530
A6: TARGET MARKET SHARE PRICE | D6: =D4*D5 -> 98.1 | E6: LESS:TARGET BOOK VALUE | I6: 30000
A7: % PREMIUM | D7: 30 | E7: EXCESS PURCHASE PRICE (X) | I7: =I5-I6 -> 97530
A8: PURCHASE PRICE | D8: 127.53 | E8: ALLOCATION TO IDENTIFIABLE INTANGIABLE | I8: 30
A9: TARGET SHARES OUTSTANDING | D9: 1000 | E9: INCREMENTAL AMORTIZABLE INTANGIBLES(y) | I9: 29259
A10: PURCHASE PRICE OF TARGET EQUITY | D10: =D8*D9 -> 127530 | E10: AMORT PERIOD (YEARS) | I10: 7 years
A11: DEBT OF TARGET REDEEMED | D11: 0 | E11: INCREMENTAL ANNUAL AMORTIZATION | I11: 4180
A12: CASH OF TARGET PURCHASED | D12: 5000
A13: ENTERPRISE VALUE | D13: =D10+D11-D12 -> 122530 | E13: INCREMENTAL GOODWILL(X)-(Y) | I13: =I7-I9 -> 68271
A15: BUYER PRICE OF SHARE ISSUANCE | D15: 50
A16: EQUITY PP SPLIT (STOCK) | D16: 30
A17: SHARES ISSUED | D17: 765.18 | E17: NOTE:AMORTIZATION OF TARGET EXISTING INTANGIBLES IS INCLUDED IN TARGET INCOME
A18: FINANCING FEES AS % OF NEW DEBT | D18: 3
A19: AMORT PERIOD (YEARS) | D19: 5 Years
A20: TOTAL AMORTIZABLE FINANCING FEES | D20: 2668
A21: ANNUAL AMORTIZATION FINANCING FEES | D21: 534
A23: INTEREST RATE ON INCREMENTAL DEBT | D23: 4 | E23: NON FINANCING FEES AS %OF ENTERPRISE
A24: INTEREST RATE ON CASH BALANCES | D24: 0.5 | E24: ENTERPRISE VALUE | I24: 1.63
A26: TAX RATE FOR INCREMENTAL EARNINGS | D26: 25
A28: PRE TAX SYNERGIES AS % OF SG&A | E28: AMOUNT OF SYNERGIES
C29: 2020 | D29: 10 | E29: $ | G29: 2210
C30: 2021 | D30: 10 | E30: $ | G30: 2570
D33: SOURCES&UESES
A35: SOURCES | E35: USES
A36: NEW BUYER DEBT | D36: 88936 | E36: PURCAHSE OF TARGET EQUITY | I36: 127530
A37: CASH OF TARGET PURCHASED | D37: 5000 | E37: DEBT OF TARGET REDEEMED | I37: 0
A38: BUYER CASH TO FUND TRANSCATION | D38: 0 | E38: TOTAL FEES | I38: 4665
A39: BUYER EQUITY ISSUED | D39: 38259
A40: TOTAL SOURCES | D40: =D36+D37+D38+D39 -> 132195 | E40: TOTAL USES | I40: =I36+I37+I38 -> 132195

Sheet ACCRETION - DILUTION
C3: STANDALONE FINANCIAL STATISTICS
G4: 2020A | H4: 2021P
A5: BUYERS STANDALONE
A6: EPS | G6: ='Buyers FS'!C27 -> 4.45 | H6: ='Buyers FS'!D27 -> 5.59
A7: DILUTED SHARES OUTSTANDING | G7: ='Buyers FS'!C26 -> 10000 | H7: ='Buyers FS'!D26 -> 10000
A8: NET INCOME | G8: =G6*G7 -> 44500 | H8: =H6*H7 -> 55900
A11: TARGET STANDALONE
A12: NET INCOME | G12: ='Target FS'!C25 -> 6540 | H12: ='Target FS'!D25 -> 8640
A14: NOTE: TARGET NET INCOME >TOTAL ADJUSTMENTS TO NET INCOME &100% DEBT -FUNDED TRANSCATION=ACCRETIVE
B17: TRANSACTION ADJUSTMENTS TO COMBINED NET INCOME
A18: PLUS:EBIT SYNERGIES | G18: =ASSUMPTIONS!G29 -> 2210 | H18: =ASSUMPTIONS!G30 -> 2570
A19: LESS:ACQUISITION CAPITAL EXPENSE
A20: INTEREST EXPENSE ON INCREMENTAL DEBT(a) | G20: 3557 | H20: =G20 -> 3557
A21: FORGONE INTEREST INCOME(b) | G21: 25 | H21: =G21 -> 25
A22: AMORT. OF FINANCING FEES | G22: =ASSUMPTIONS!D21 -> 534 | H22: =G22 -> 534
A23: LESS:INCREMENTAL AMORT.OF TRANSACTION INTANGIBLES | G23: =ASSUMPTIONS!I11 -> 4180 | H23: =G23 -> 4180
A24: TOTAL PRE-TAX ADJUSTMENTS | G24: =G18-G20-G21-G22-G23 -> -6086 | H24: =H18-H20-H21-H22-H23 -> -5726
A25: INCREMENTAL TAX EXPENSE/(BENEFIT) | F25: =ASSUMPTIONS!D26 -> 25 | G25: =G24*F25 -> -152150 | H25: =H24*F25 -> -143150
A26: TOTAL ADJUSTMENTS TO NET INCOME | G26: =G24*75% -> -4564.5 | H26: =H24*75% -> -4294.5
B28: PRO FORMA COMBINED RESULTS
A29: NET INCOME | G29: =G8+G12+G26 -> 46475.5 | H29: =H8+H12+H26 -> 60245.5
A30: DILUTED SHARES OUTSTANDING (EXISTING) | G30: ='Buyers FS'!C26 -> 10000 | H30: =G30 -> 10000
A31: DILUTEDSHARES OUTSTANDING (SHARES ISSUED) | G31: =ASSUMPTIONS!D39/ASSUMPTIONS!D15 -> 765.18 | H31: =ASSUMPTIONS!D39/ASSUMPTIONS!D15 -> 765.18
A32: TOTAL DILUTED SHARES OUTSTANDING | G32: =G30+G31 -> 10765.18 | H32: =H30+H31 -> 10765.18
A33: EPS | G33: =G29/G32 -> 4.317206 | H33: =H29/H32 -> 5.59633
B35: ACCRETION/DILUTION
A36: EPS $ ACCRETION /(DILUTION) | G36: =G33-G6 -> -0.13279397 | H36: =H33-H6 -> 0.0063300196
A37: EPS % ACCRETION /(DILUTION) | G37: -3 | H37: 0.01
A38: ADDITIONAL PRE TAX SYNERGIES TO BREAK EVEN | G38: 2634

Sheet TRANSACTION BS
C3: BUYER | D3: TARGET | E3: ADJUSTMENTS | G3: PRO FORMA
C4: 2020A | D4: 2020A | E4: + | F4: - | G4: 20204
A5: CASH | C5: ='Buyers FS'!B31 -> 50000 | D5: ='Target FS'!B31 -> 5000 | F5: =D5 -> 5000 | G5: =C5 -> 50000
A6: ACCOUNTS RECEIVABLES | C6: ='Buyers FS'!B32 -> 120000 | D6: ='Target FS'!B32 -> 25000 | G6: =C6+D6 -> 145000
A7: INVENTORY | C7: ='Buyers FS'!B33 -> 25000 | D7: ='Target FS'!B33 -> 6000 | G7: =C7+D7 -> 31000
A8: CURRENT ASSESTS | C8: ='Buyers FS'!B34 -> 195000 | D8: ='Target FS'!B34 -> 36000 | G8: =C8+D8 -> 231000
A10: NET PP&E | C10: ='Buyers FS'!B36 -> 20000 | D10: ='Target FS'!B36 -> 7000 | G10: =C10+D10 -> 27000
A11: INTANGIABLE ASSESTS | C11: ='Buyers FS'!B37 -> 0 | D11: ='Target FS'!B37 -> 0 | E11: =ASSUMPTIONS!I9 -> 29259 | G11: =E11 -> 29259
A12: GOODWILL | C12: ='Buyers FS'!B38 -> 0 | D12: ='Target FS'!B38 -> 0 | E12: =ASSUMPTIONS!I13 -> 68271 | G12: =E12 -> 68271
A13: DEFERRED FINANCING FEES | C13: 0 | D13: 0 | E13: =ASSUMPTIONS!D20 -> 2668 | G13: =E13 -> 2668
A14: TOTAL ASSESTS | C14: ='Buyers FS'!B39 -> 215000 | D14: ='Target FS'!B39 -> 43000 | G14: =G8+G10+G12+G11+G13 -> 358198
A16: CURRENT LIABILITIES | C16: ='Buyers FS'!B41 -> 130000 | D16: ='Target FS'!B41 -> 13000 | G16: =C16+D16 -> 143000
A17: BANK DEBT | C17: 0 | D17: 0 | F17: =ASSUMPTIONS!D36 -> 88936 | G17: 88936
A18: TOTAL LIABILITIES | C18: ='Buyers FS'!B43 -> 130000 | D18: ='Target FS'!B43 -> 13000 | G18: =G16+G17 -> 231936
A20: SHAREHOLDERS EQUITY | C20: ='Buyers FS'!B45 -> 85000 | D20: ='Target FS'!B45 -> 30000 | E20: =+ASSUMPTIONS!D39-(ASSUMPTIONS!I38-ASSUMPTIONS!D20) -> 36262 | F20: =D20 -> 30000 | G20: =C20+D20+E20-F20 -> 121262
A21: TOTAL LIABILITIES $SH EQUITY | C21: ='Buyers FS'!B46 -> 215000 | D21: ='Target FS'!B46 -> 43000 | G21: =G18+G20 -> 353198
